{
  "meta": {
    "generatedAt": "2026-03-24T22:08:18.626Z",
    "sourceKind": "official-xml",
    "sourceDate": "2026-03-20T00:27:38.159+01:00",
    "sourceLabel": "Official EU FSF XML export",
    "sourceFileName": "full_sanctions_list_1_1.xml",
    "globalFileId": "181813",
    "ingestionMode": "local-xml"
  },
  "metrics": {
    "recordCount": 5819,
    "previousRecordCount": 5819,
    "recordDelta": 0,
    "personCount": 4323,
    "entityCount": 1496,
    "aliasTotal": 23561,
    "entriesWithAliases": 5113,
    "aliasCoveragePct": 87.9,
    "latestPublicationDate": "2026-01-29",
    "matcherDatasetBytes": 2332486,
    "rawXmlBytes": 24099325,
    "topProgrammes": [
      {
        "programme": "UKR",
        "count": 2596
      },
      {
        "programme": "IRN",
        "count": 692
      },
      {
        "programme": "SYR",
        "count": 380
      },
      {
        "programme": "BLR",
        "count": 369
      },
      {
        "programme": "TAQA",
        "count": 344
      }
    ]
  },
  "checks": [
    {
      "id": "source-access",
      "label": "Source access",
      "status": "healthy",
      "detail": "Official FSF XML available via local-xml (full_sanctions_list_1_1.xml)."
    },
    {
      "id": "parse",
      "label": "Parse step",
      "status": "healthy",
      "detail": "5,819 entities parsed with 23,561 aliases retained."
    },
    {
      "id": "freshness",
      "label": "Source freshness",
      "status": "watch",
      "detail": "Source export is 118.7 hours old."
    },
    {
      "id": "publish",
      "label": "Publish step",
      "status": "healthy",
      "detail": "Matcher dataset written successfully at 2.22 MB."
    },
    {
      "id": "coverage",
      "label": "Alias coverage",
      "status": "healthy",
      "detail": "87.9% of entities carry at least one alias in the generated dataset."
    }
  ]
}
